codeworks/__init__.py
codeworks/setup.py
codeworks/hello_world/__init__.py
codeworks/hello_world/hello_world.py
codeworks-0.0.2rc38.post1.dist-info/LICENSE
codeworks-0.0.2rc38.post1.dist-info/WHEEL
codeworks-0.0.2rc38.post1.dist-info/METADATA
codeworks-0.0.2rc38.post1.dist-info/RECORD
